mlopsrobotics/azure/API_use.py
mlopsrobotics/azure/LOC_hyperparametingtuning.py
mlopsrobotics/azure/PipelineScheduler.py
mlopsrobotics/azure/endpoint_inference_LOC.py
mlopsrobotics/azure/endpoint_inference_YOLO.py
mlopsrobotics/azure/pipeline_inference.py
mlopsrobotics/azure/pipeline_train_loc.py
mlopsrobotics/azure/pipeline_train_loc_scheduler.py
mlopsrobotics/azure/pipeline_train_yolo.py
mlopsrobotics/azure/pipeline_train_yolo_scheduler.py
mlopsrobotics/azure/register_model.py
mlopsrobotics/azure/setup_data.py
mlopsrobotics/azure/setup_trainingjob.py
mlopsrobotics/azure/traincostanalysis.py
mlopsrobotics/logs/inference.log
mlopsrobotics/pypi.py
mlopsrobotics-0.2.dist-info/METADATA
mlopsrobotics-0.2.dist-info/WHEEL
mlopsrobotics-0.2.dist-info/RECORD
