Metadata-Version: 2.1
Name: mlopsrobotics
Version: 0.2
Summary: 
Author: MichaelNed
Author-email: 213566@buas.nl
Requires-Python: >=3.8.1,<4.0
Classifier: Programming Language :: Python :: 3
Classifier: Programming Language :: Python :: 3.9
Classifier: Programming Language :: Python :: 3.10
Classifier: Programming Language :: Python :: 3.11
Requires-Dist: ansimarkup (>=1.5.0,<2.0.0)
Requires-Dist: autopep8 (>=2.0.2,<3.0.0)
Requires-Dist: azure-ai-ml (>=1.7.2,<2.0.0)
Requires-Dist: azure-identity (>=1.13.0,<2.0.0)
Requires-Dist: azure-keyvault-secrets (>=4.7.0,<5.0.0)
Requires-Dist: azureml (>=0.2.7,<0.3.0)
Requires-Dist: azureml-core (>=1.51.0,<2.0.0)
Requires-Dist: azureml-dataset-runtime (>=1.51.0,<2.0.0)
Requires-Dist: azureml-mlflow (>=1.51.0,<2.0.0)
Requires-Dist: black (>=23.3.0,<24.0.0)
Requires-Dist: fastapi (>=0.97.0,<0.98.0)
Requires-Dist: flake8 (>=6.0.0,<7.0.0)
Requires-Dist: gym (>=0.26.2,<0.27.0)
Requires-Dist: gymnasium (>=0.28.1,<0.29.0)
Requires-Dist: h5py (>=3.8.0,<4.0.0)
Requires-Dist: loguru (>=0.7.0,<0.8.0)
Requires-Dist: matplotlib (>=3.7.1,<4.0.0)
Requires-Dist: mldesigner (>=0.1.0b13,<0.2.0)
Requires-Dist: mlflow (>=2.3.2,<3.0.0)
Requires-Dist: mujoco (>=2.3.5,<3.0.0)
Requires-Dist: mypy (>=1.4.0,<2.0.0)
Requires-Dist: numpy (>=1.19.3,<2.0.0)
Requires-Dist: opencv-python-headless (>=4.5.0.72,<5.0.0.0)
Requires-Dist: pandas (>=2.0.1,<3.0.0)
Requires-Dist: pillow (>=9.5.0,<10.0.0)
Requires-Dist: poetry2conda (>=0.3.0,<0.4.0)
Requires-Dist: pre-commit (>=3.3.3,<4.0.0)
Requires-Dist: psutil (>=5.9.5,<6.0.0)
Requires-Dist: pyarrow (>=8.0.0,<9.0.0)
Requires-Dist: pytest (>=7.3.1,<8.0.0)
Requires-Dist: python-multipart (>=0.0.6,<0.0.7)
Requires-Dist: pyyaml (>=6.0,<7.0)
Requires-Dist: requests (>=2.30.0,<3.0.0)
Requires-Dist: roboflow (>=1.0.8,<2.0.0)
Requires-Dist: robosuite (>=1.4.0,<2.0.0)
Requires-Dist: seaborn (>=0.12.2,<0.13.0)
Requires-Dist: setuptools (>=67.8.0,<68.0.0)
Requires-Dist: sphinx (>=4.3.0,<5.0.0)
Requires-Dist: sphinx-autobuild (>=2021.3.14,<2022.0.0)
Requires-Dist: sphinx-rtd-theme (>=1.2.0,<2.0.0)
Requires-Dist: termcolor (>=2.3.0,<3.0.0)
Requires-Dist: torch (>=2.0.0,<3.0.0)
Requires-Dist: torchaudio (>=2.0.2,<3.0.0)
Requires-Dist: torchvision (>=0.15.1,<0.16.0)
Requires-Dist: tqdm (>=4.65.0,<5.0.0)
Requires-Dist: ultralytics (>=8.0.101,<9.0.0)
Requires-Dist: uvicorn (>=0.22.0,<0.23.0)
Requires-Dist: wandb (>=0.15.3,<0.16.0)
